{
    "logs": [
        {
            "outputFile": "F:\\Courses\\Android\\Android Projects\\Projects group\\Temp App\\app\\build\\intermediates\\incremental\\mergeDebugResources\\merged.dir\\values-ldltr-v21\\values-ldltr-v21.xml",
            "map": [
                {
                    "source": "C:\\Users\\mmekk\\.gradle\\caches\\transforms-1\\files-1.1\\appcompat-v7-27.1.1.aar\\a9a33ec0a66238c834e35ae9963dc833\\res\\values-ldltr-v21\\values-ldltr-v21.xml",
                    "from": {
                        "startLines": "2",
                        "startColumns": "4",
                        "startOffsets": "55",
                        "endColumns": "112",
                        "endOffsets": "163"
                    }
                }
            ]
        }
    ]
}